[
  {
    "image": "../images/projects/melodify.png",
    "title": "Melodify",
    "description": "Spotify interface with user stats, music videos, pane views, suggestions, and more",
    "tags": ["cSharp", "wpf", "spotify", "api"],
    "website": "https://github.com/novatorem/Melodify"
  },
  {
    "image": "../images/projects/coverhack.png",
    "title": "Cover Hack",
    "description": "Create custom cover letters where users can input reactive fields",
    "tags": ["react", "mongoose", "node", "fullstack"],
    "website": "https://cover-hack.novac.dev/",
    "github": "https://github.com/novatorem/Cover-Hack"
  },
  {
    "image": "../images/projects/streamweaver.png",
    "title": "StreamWeaver",
    "description": "A cross-platform application for virtual events and performances, transmitting data globally",
    "tags": ["c#", "networking", "srt", "cross-platform"],
    "github": "https://www.liminalet.com/streamweaver-lite"
  },
  {
    "image": "../images/projects/robotics.png",
    "title": "Robotics",
    "description": "Collision detection, integrated motion planning, dynamic tracking, and pathing",
    "tags": ["python", "robots", "paths", "algorithms"],
    "github": "https://github.com/novatorem/Robotics"
  },
  {
    "image": "../images/projects/facial.png",
    "title": "FacialRecognition",
    "description": "A trained python program that takes an mp4 and identifies all faces in the video",
    "tags": ["numpy", "ml", "ai", "cv"],
    "github": "https://github.com/novatorem/FacialRecognition"
  },
  {
    "image": "../images/projects/era.png",
    "title": "Emergency Response Aid",
    "description": "Team application designed as an intermediatery to help users seek medical attention",
    "tags": ["android", "java", "mongodb", "app"],
    "github": "https://github.com/novatorem/ERA-Emergency-Response-Aid"
  }
]
